[
    { "job_id": 1, "user_id": 1, "title": "Logo Design", "description": "Looking for a creative logo designer.", "Price": 1000 },
    { "job_id": 2, "user_id": 1, "title": "Mobile App Promotion", "description": "Need help advertising a newly built application.", "Price": 10000 },
    
    { "job_id": 3, "user_id": 2, "title": "Website Development", "description": "Seeking a web developer for a portfolio site.", "Price": 5000 },
    { "job_id": 4, "user_id": 2, "title": "SEO Optimization", "description": "Need an expert to optimize website SEO.", "Price": 2500 },
    
    { "job_id": 5, "user_id": 3, "title": "Social Media Marketing", "description": "Want a marketer to manage social media campaigns.", "Price": 7000 },
    { "job_id": 6, "user_id": 3, "title": "Graphic Design", "description": "Require designs for business branding.", "Price": 3000 },
    
    { "job_id": 7, "user_id": 4, "title": "Database Management", "description": "Need assistance in optimizing SQL databases.", "Price": 8000 },
    { "job_id": 8, "user_id": 4, "title": "E-commerce Website", "description": "Looking for a developer to build an online store.", "Price": 12000 },
    
    { "job_id": 9, "user_id": 5, "title": "Cybersecurity Audit", "description": "Require security audit for enterprise systems.", "Price": 15000 },
    { "job_id": 10, "user_id": 5, "title": "Penetration Testing", "description": "Need ethical hacking services.", "Price": 20000 },
    
    { "job_id": 11, "user_id": 6, "title": "Content Writing", "description": "Seeking blog writers for tech articles.", "Price": 4000 },
    { "job_id": 12, "user_id": 6, "title": "Technical Documentation", "description": "Need documentation for a SaaS product.", "Price": 6000 },
    
    { "job_id": 13, "user_id": 7, "title": "Video Editing", "description": "Looking for a skilled video editor.", "Price": 5000 },
    { "job_id": 14, "user_id": 7, "title": "Animation", "description": "Need an animator for an explainer video.", "Price": 9000 },
    
    { "job_id": 15, "user_id": 8, "title": "UI/UX Design", "description": "Seeking a UI/UX expert for a mobile app.", "Price": 7500 },
    { "job_id": 16, "user_id": 8, "title": "Product Design", "description": "Looking for an industrial product designer.", "Price": 11000 },
    
    { "job_id": 17, "user_id": 9, "title": "Music Production", "description": "Need a producer to mix and master tracks.", "Price": 6500 },
    { "job_id": 18, "user_id": 9, "title": "Voice Over", "description": "Looking for a professional voice-over artist.", "Price": 5500 },
    
    { "job_id": 19, "user_id": 10, "title": "Blockchain Development", "description": "Require a blockchain developer for a project.", "Price": 25000 },
    { "job_id": 20, "user_id": 10, "title": "Smart Contract Audit", "description": "Need an expert to audit Ethereum smart contracts.", "Price": 18000 }
]